xpyxl/__init__.py
xpyxl/_workbook.py
xpyxl/builders.py
xpyxl/nodes.py
xpyxl/py.typed
xpyxl/render.py
xpyxl/styles.py
xpyxl/engines/__init__.py
xpyxl/engines/base.py
xpyxl/engines/html_engine.py
xpyxl/engines/hybrid_engine.py
xpyxl/engines/openpyxl_engine.py
xpyxl/engines/xlsxwriter_engine.py
xpyxl-0.7.3.dist-info/METADATA
xpyxl-0.7.3.dist-info/WHEEL
xpyxl-0.7.3.dist-info/top_level.txt
xpyxl-0.7.3.dist-info/RECORD
