Metadata-Version: 2.4
Name: xpyxl
Version: 0.7.3
Summary: Create styled excel reports with declarative python.
Author-email: dakixr <dakixr@gmail.com>
Requires-Python: >=3.12
Requires-Dist: openpyxl>=3.1.5
Requires-Dist: xlsxwriter>=3.1.0
